{
    "acc1": 0.7104143747708104,
    "acc5": [
        0.923028969563623
    ],
    "mean_per_class_recall": 0.7115458664408986,
    "classification_report": {
        "0": {
            "precision": 0.9238938053097345,
            "recall": 0.8432956381260097,
            "f1-score": 0.8817567567567568,
            "support": 619.0
        },
        "1": {
            "precision": 0.8043052837573386,
            "recall": 0.9319727891156463,
            "f1-score": 0.8634453781512605,
            "support": 441.0
        },
        "2": {
            "precision": 0.7857142857142857,
            "recall": 0.6657496561210454,
            "f1-score": 0.7207743857036486,
            "support": 727.0
        },
        "3": {
            "precision": 0.6403712296983759,
            "recall": 0.6013071895424836,
            "f1-score": 0.6202247191011236,
            "support": 459.0
        },
        "4": {
            "precision": 0.8044444444444444,
            "recall": 0.8227272727272728,
            "f1-score": 0.8134831460674158,
            "support": 440.0
        },
        "5": {
            "precision": 0.9690721649484536,
            "recall": 0.9195652173913044,
            "f1-score": 0.9436698271054099,
            "support": 920.0
        },
        "6": {
            "precision": 0.5779467680608364,
            "recall": 0.5577981651376147,
            "f1-score": 0.5676937441643324,
            "support": 545.0
        },
        "7": {
            "precision": 0.4056603773584906,
            "recall": 0.6703786191536748,
            "f1-score": 0.5054575986565911,
            "support": 449.0
        },
        "8": {
            "precision": 0.6551724137931034,
            "recall": 0.8719806763285024,
            "f1-score": 0.7481865284974093,
            "support": 414.0
        },
        "9": {
            "precision": 0.3128621089223638,
            "recall": 0.8035714285714286,
            "f1-score": 0.45037531276063386,
            "support": 336.0
        },
        "10": {
            "precision": 0.7734806629834254,
            "recall": 0.6687898089171974,
            "f1-score": 0.71733561058924,
            "support": 628.0
        },
        "11": {
            "precision": 0.7041237113402062,
            "recall": 0.85375,
            "f1-score": 0.7717514124293785,
            "support": 800.0
        },
        "12": {
            "precision": 0.9240506329113924,
            "recall": 0.8996478873239436,
            "f1-score": 0.911685994647636,
            "support": 568.0
        },
        "13": {
            "precision": 0.7094188376753507,
            "recall": 0.8489208633093526,
            "f1-score": 0.7729257641921398,
            "support": 417.0
        },
        "14": {
            "precision": 0.7292724196277496,
            "recall": 0.7219430485762144,
            "f1-score": 0.7255892255892256,
            "support": 597.0
        },
        "15": {
            "precision": 0.632183908045977,
            "recall": 0.4241645244215938,
            "f1-score": 0.5076923076923077,
            "support": 389.0
        },
        "16": {
            "precision": 0.5843621399176955,
            "recall": 0.5867768595041323,
            "f1-score": 0.5855670103092784,
            "support": 484.0
        },
        "17": {
            "precision": 0.8919753086419753,
            "recall": 0.7372448979591837,
            "f1-score": 0.8072625698324022,
            "support": 392.0
        },
        "18": {
            "precision": 0.7317073170731707,
            "recall": 0.3076923076923077,
            "f1-score": 0.4332129963898917,
            "support": 390.0
        },
        "19": {
            "precision": 0.8253968253968254,
            "recall": 0.8987654320987655,
            "f1-score": 0.8605200945626478,
            "support": 405.0
        },
        "20": {
            "precision": 0.36280137772675086,
            "recall": 0.8586956521739131,
            "f1-score": 0.510088781275222,
            "support": 368.0
        },
        "21": {
            "precision": 0.9318181818181818,
            "recall": 0.6493212669683258,
            "f1-score": 0.7653333333333333,
            "support": 442.0
        },
        "22": {
            "precision": 0.9116279069767442,
            "recall": 0.7788079470198676,
            "f1-score": 0.84,
            "support": 755.0
        },
        "23": {
            "precision": 0.7491638795986622,
            "recall": 0.5803108808290155,
            "f1-score": 0.654014598540146,
            "support": 386.0
        },
        "24": {
            "precision": 0.8786279683377308,
            "recall": 0.8141809290953546,
            "f1-score": 0.8451776649746193,
            "support": 409.0
        },
        "25": {
            "precision": 0.5417406749555951,
            "recall": 0.6314699792960663,
            "f1-score": 0.5831739961759083,
            "support": 483.0
        },
        "26": {
            "precision": 0.8087091757387247,
            "recall": 0.7624633431085044,
            "f1-score": 0.7849056603773585,
            "support": 682.0
        },
        "27": {
            "precision": 0.9216417910447762,
            "recall": 0.8111658456486043,
            "f1-score": 0.862882096069869,
            "support": 609.0
        },
        "28": {
            "precision": 0.6003649635036497,
            "recall": 0.8204488778054863,
            "f1-score": 0.6933614330874605,
            "support": 401.0
        },
        "29": {
            "precision": 0.8560490045941807,
            "recall": 0.8987138263665595,
            "f1-score": 0.8768627450980392,
            "support": 622.0
        },
        "30": {
            "precision": 0.9371816638370118,
            "recall": 0.8652037617554859,
            "f1-score": 0.8997555012224939,
            "support": 638.0
        },
        "31": {
            "precision": 0.6551724137931034,
            "recall": 0.23623445825932504,
            "f1-score": 0.3472584856396867,
            "support": 563.0
        },
        "32": {
            "precision": 0.5630252100840336,
            "recall": 0.29910714285714285,
            "f1-score": 0.39067055393586003,
            "support": 448.0
        },
        "33": {
            "precision": 0.7405247813411079,
            "recall": 0.7257142857142858,
            "f1-score": 0.733044733044733,
            "support": 700.0
        },
        "34": {
            "precision": 0.5633802816901409,
            "recall": 0.8556149732620321,
            "f1-score": 0.6794055201698513,
            "support": 374.0
        },
        "35": {
            "precision": 0.42302158273381296,
            "recall": 0.7067307692307693,
            "f1-score": 0.5292529252925292,
            "support": 416.0
        },
        "36": {
            "precision": 0.6514657980456026,
            "recall": 0.7874015748031497,
            "f1-score": 0.7130124777183601,
            "support": 508.0
        },
        "37": {
            "precision": 0.8339622641509434,
            "recall": 0.7072,
            "f1-score": 0.7653679653679654,
            "support": 625.0
        },
        "38": {
            "precision": 0.9049235993208828,
            "recall": 0.9433628318584071,
            "f1-score": 0.9237435008665511,
            "support": 565.0
        },
        "39": {
            "precision": 0.702054794520548,
            "recall": 0.8836206896551724,
            "f1-score": 0.7824427480916031,
            "support": 696.0
        },
        "40": {
            "precision": 0.6818181818181818,
            "recall": 0.038860103626943004,
            "f1-score": 0.07352941176470588,
            "support": 386.0
        },
        "41": {
            "precision": 0.5796847635726795,
            "recall": 0.5572390572390572,
            "f1-score": 0.5682403433476395,
            "support": 594.0
        },
        "42": {
            "precision": 0.3876698014629049,
            "recall": 0.8568129330254042,
            "f1-score": 0.5338129496402878,
            "support": 433.0
        },
        "43": {
            "precision": 0.8652849740932642,
            "recall": 0.8119935170178282,
            "f1-score": 0.8377926421404682,
            "support": 617.0
        },
        "44": {
            "precision": 0.825,
            "recall": 0.028472821397756688,
            "f1-score": 0.05504587155963303,
            "support": 1159.0
        },
        "45": {
            "precision": 0.8445229681978799,
            "recall": 0.8770642201834863,
            "f1-score": 0.8604860486048604,
            "support": 545.0
        },
        "46": {
            "precision": 0.9170593779453345,
            "recall": 0.9759277833500501,
            "f1-score": 0.9455782312925171,
            "support": 997.0
        },
        "47": {
            "precision": 0.4831804281345566,
            "recall": 0.7688564476885644,
            "f1-score": 0.5934272300469483,
            "support": 411.0
        },
        "48": {
            "precision": 0.8487903225806451,
            "recall": 0.8680412371134021,
            "f1-score": 0.8583078491335372,
            "support": 485.0
        },
        "49": {
            "precision": 0.8731117824773413,
            "recall": 0.5422138836772983,
            "f1-score": 0.6689814814814815,
            "support": 533.0
        },
        "accuracy": 0.7103777044371103,
        "macro avg": {
            "precision": 0.7245758911943233,
            "recall": 0.7115458664408986,
            "f1-score": 0.6876713432498479,
            "support": 27270.0
        },
        "weighted avg": {
            "precision": 0.7493780693564296,
            "recall": 0.7103777044371103,
            "f1-score": 0.6961614822499131,
            "support": 27270.0
        }
    }
}