{
    "acc1": 0.7148881554822148,
    "acc5": [
        0.9308030803080308
    ],
    "mean_per_class_recall": 0.7120141542745198,
    "classification_report": {
        "0": {
            "precision": 0.9086206896551724,
            "recall": 0.851373182552504,
            "f1-score": 0.8790658882402002,
            "support": 619.0
        },
        "1": {
            "precision": 0.7907869481765835,
            "recall": 0.9342403628117913,
            "f1-score": 0.8565488565488566,
            "support": 441.0
        },
        "2": {
            "precision": 0.7350901525658807,
            "recall": 0.7290233837689133,
            "f1-score": 0.7320441988950276,
            "support": 727.0
        },
        "3": {
            "precision": 0.6197478991596639,
            "recall": 0.6427015250544662,
            "f1-score": 0.6310160427807486,
            "support": 459.0
        },
        "4": {
            "precision": 0.8171296296296297,
            "recall": 0.8022727272727272,
            "f1-score": 0.8096330275229358,
            "support": 440.0
        },
        "5": {
            "precision": 0.9747126436781609,
            "recall": 0.9217391304347826,
            "f1-score": 0.9474860335195531,
            "support": 920.0
        },
        "6": {
            "precision": 0.5673400673400674,
            "recall": 0.618348623853211,
            "f1-score": 0.591747146619842,
            "support": 545.0
        },
        "7": {
            "precision": 0.405777166437414,
            "recall": 0.6570155902004454,
            "f1-score": 0.5017006802721088,
            "support": 449.0
        },
        "8": {
            "precision": 0.6529516994633273,
            "recall": 0.8816425120772947,
            "f1-score": 0.750256937307297,
            "support": 414.0
        },
        "9": {
            "precision": 0.3072562358276644,
            "recall": 0.8065476190476191,
            "f1-score": 0.44499178981937604,
            "support": 336.0
        },
        "10": {
            "precision": 0.7221324717285945,
            "recall": 0.7117834394904459,
            "f1-score": 0.7169206094627105,
            "support": 628.0
        },
        "11": {
            "precision": 0.6925373134328359,
            "recall": 0.87,
            "f1-score": 0.771191135734072,
            "support": 800.0
        },
        "12": {
            "precision": 0.9239130434782609,
            "recall": 0.897887323943662,
            "f1-score": 0.9107142857142857,
            "support": 568.0
        },
        "13": {
            "precision": 0.6635687732342007,
            "recall": 0.8561151079136691,
            "f1-score": 0.7476439790575916,
            "support": 417.0
        },
        "14": {
            "precision": 0.7303754266211604,
            "recall": 0.7169179229480737,
            "f1-score": 0.7235841081994928,
            "support": 597.0
        },
        "15": {
            "precision": 0.6477732793522267,
            "recall": 0.41131105398457585,
            "f1-score": 0.5031446540880503,
            "support": 389.0
        },
        "16": {
            "precision": 0.5947136563876652,
            "recall": 0.5578512396694215,
            "f1-score": 0.5756929637526652,
            "support": 484.0
        },
        "17": {
            "precision": 0.8790560471976401,
            "recall": 0.7602040816326531,
            "f1-score": 0.8153214774281806,
            "support": 392.0
        },
        "18": {
            "precision": 0.6988636363636364,
            "recall": 0.3153846153846154,
            "f1-score": 0.43462897526501765,
            "support": 390.0
        },
        "19": {
            "precision": 0.8231292517006803,
            "recall": 0.8962962962962963,
            "f1-score": 0.8581560283687943,
            "support": 405.0
        },
        "20": {
            "precision": 0.37037037037037035,
            "recall": 0.842391304347826,
            "f1-score": 0.5145228215767634,
            "support": 368.0
        },
        "21": {
            "precision": 0.9142011834319527,
            "recall": 0.6990950226244343,
            "f1-score": 0.7923076923076923,
            "support": 442.0
        },
        "22": {
            "precision": 0.9049079754601227,
            "recall": 0.7814569536423841,
            "f1-score": 0.8386638237384506,
            "support": 755.0
        },
        "23": {
            "precision": 0.739413680781759,
            "recall": 0.5880829015544041,
            "f1-score": 0.6551226551226551,
            "support": 386.0
        },
        "24": {
            "precision": 0.8661417322834646,
            "recall": 0.8068459657701712,
            "f1-score": 0.8354430379746836,
            "support": 409.0
        },
        "25": {
            "precision": 0.5731225296442688,
            "recall": 0.6004140786749482,
            "f1-score": 0.5864509605662285,
            "support": 483.0
        },
        "26": {
            "precision": 0.7981651376146789,
            "recall": 0.7653958944281525,
            "f1-score": 0.781437125748503,
            "support": 682.0
        },
        "27": {
            "precision": 0.9292543021032504,
            "recall": 0.7980295566502463,
            "f1-score": 0.8586572438162544,
            "support": 609.0
        },
        "28": {
            "precision": 0.6063432835820896,
            "recall": 0.8104738154613467,
            "f1-score": 0.6937033084311632,
            "support": 401.0
        },
        "29": {
            "precision": 0.8621745788667687,
            "recall": 0.905144694533762,
            "f1-score": 0.8831372549019608,
            "support": 622.0
        },
        "30": {
            "precision": 0.9485420240137221,
            "recall": 0.8667711598746082,
            "f1-score": 0.9058149058149059,
            "support": 638.0
        },
        "31": {
            "precision": 0.6402877697841727,
            "recall": 0.15808170515097691,
            "f1-score": 0.2535612535612536,
            "support": 563.0
        },
        "32": {
            "precision": 0.5625,
            "recall": 0.32142857142857145,
            "f1-score": 0.4090909090909091,
            "support": 448.0
        },
        "33": {
            "precision": 0.7813504823151125,
            "recall": 0.6942857142857143,
            "f1-score": 0.735249621785174,
            "support": 700.0
        },
        "34": {
            "precision": 0.58195211786372,
            "recall": 0.8449197860962567,
            "f1-score": 0.6892039258451472,
            "support": 374.0
        },
        "35": {
            "precision": 0.4177777777777778,
            "recall": 0.6778846153846154,
            "f1-score": 0.5169569202566453,
            "support": 416.0
        },
        "36": {
            "precision": 0.6583333333333333,
            "recall": 0.7775590551181102,
            "f1-score": 0.7129963898916968,
            "support": 508.0
        },
        "37": {
            "precision": 0.8742393509127789,
            "recall": 0.6896,
            "f1-score": 0.7710196779964222,
            "support": 625.0
        },
        "38": {
            "precision": 0.9041095890410958,
            "recall": 0.9345132743362832,
            "f1-score": 0.9190600522193212,
            "support": 565.0
        },
        "39": {
            "precision": 0.7158018867924528,
            "recall": 0.8721264367816092,
            "f1-score": 0.7862694300518135,
            "support": 696.0
        },
        "40": {
            "precision": 0.4166666666666667,
            "recall": 0.012953367875647668,
            "f1-score": 0.02512562814070352,
            "support": 386.0
        },
        "41": {
            "precision": 0.5706618962432916,
            "recall": 0.5370370370370371,
            "f1-score": 0.5533391153512576,
            "support": 594.0
        },
        "42": {
            "precision": 0.39912758996728465,
            "recall": 0.8452655889145496,
            "f1-score": 0.5422222222222223,
            "support": 433.0
        },
        "43": {
            "precision": 0.8240887480190174,
            "recall": 0.8427876823338736,
            "f1-score": 0.8333333333333334,
            "support": 617.0
        },
        "44": {
            "precision": 0.9542857142857143,
            "recall": 0.14408973252804141,
            "f1-score": 0.25037481259370314,
            "support": 1159.0
        },
        "45": {
            "precision": 0.8462897526501767,
            "recall": 0.8788990825688073,
            "f1-score": 0.8622862286228623,
            "support": 545.0
        },
        "46": {
            "precision": 0.9121495327102803,
            "recall": 0.9789368104312939,
            "f1-score": 0.9443638122883405,
            "support": 997.0
        },
        "47": {
            "precision": 0.6043010752688172,
            "recall": 0.683698296836983,
            "f1-score": 0.6415525114155252,
            "support": 411.0
        },
        "48": {
            "precision": 0.8580246913580247,
            "recall": 0.8597938144329897,
            "f1-score": 0.858908341915551,
            "support": 485.0
        },
        "49": {
            "precision": 0.8529411764705882,
            "recall": 0.5440900562851783,
            "f1-score": 0.6643757159221076,
            "support": 533.0
        },
        "accuracy": 0.7146314631463146,
        "macro avg": {
            "precision": 0.7208600396208642,
            "recall": 0.7120141542745198,
            "f1-score": 0.6903207910220012,
            "support": 27270.0
        },
        "weighted avg": {
            "precision": 0.7495117173187942,
            "recall": 0.7146314631463146,
            "f1-score": 0.7032658522412878,
            "support": 27270.0
        }
    }
}