{
    "acc1": 0.7969821175958504,
    "acc5": [
        0.9505966846820705
    ],
    "mean_per_class_recall": 0.7831707504306296,
    "classification_report": {
        "0": {
            "precision": 0.6214285714285714,
            "recall": 0.22774869109947643,
            "f1-score": 0.3333333333333333,
            "support": 382.0
        },
        "1": {
            "precision": 0.7827380952380952,
            "recall": 0.42487883683360256,
            "f1-score": 0.5507853403141362,
            "support": 619.0
        },
        "2": {
            "precision": 0.665929203539823,
            "recall": 0.6967592592592593,
            "f1-score": 0.6809954751131222,
            "support": 432.0
        },
        "3": {
            "precision": 0.9316596931659693,
            "recall": 0.9780380673499268,
            "f1-score": 0.9542857142857143,
            "support": 683.0
        },
        "4": {
            "precision": 0.8898071625344353,
            "recall": 0.95,
            "f1-score": 0.918918918918919,
            "support": 680.0
        },
        "5": {
            "precision": 0.96,
            "recall": 0.22119815668202766,
            "f1-score": 0.3595505617977528,
            "support": 434.0
        },
        "6": {
            "precision": 0.9580246913580247,
            "recall": 0.9216152019002375,
            "f1-score": 0.9394673123486683,
            "support": 421.0
        },
        "7": {
            "precision": 0.17114914425427874,
            "recall": 0.16279069767441862,
            "f1-score": 0.16686531585220502,
            "support": 430.0
        },
        "8": {
            "precision": 0.8454545454545455,
            "recall": 0.9356136820925554,
            "f1-score": 0.8882521489971347,
            "support": 497.0
        },
        "9": {
            "precision": 0.4711168164313222,
            "recall": 0.9607329842931938,
            "f1-score": 0.632213608957795,
            "support": 382.0
        },
        "10": {
            "precision": 0.9858156028368794,
            "recall": 0.9328859060402684,
            "f1-score": 0.9586206896551724,
            "support": 447.0
        },
        "11": {
            "precision": 0.9018264840182648,
            "recall": 0.9587378640776699,
            "f1-score": 0.9294117647058824,
            "support": 412.0
        },
        "12": {
            "precision": 0.9166666666666666,
            "recall": 0.6100178890876565,
            "f1-score": 0.7325456498388829,
            "support": 559.0
        },
        "13": {
            "precision": 0.5981308411214953,
            "recall": 0.78239608801956,
            "f1-score": 0.6779661016949152,
            "support": 409.0
        },
        "14": {
            "precision": 0.9674329501915708,
            "recall": 0.9674329501915708,
            "f1-score": 0.9674329501915708,
            "support": 522.0
        },
        "15": {
            "precision": 0.8775933609958506,
            "recall": 0.7761467889908257,
            "f1-score": 0.8237585199610516,
            "support": 545.0
        },
        "16": {
            "precision": 0.5342105263157895,
            "recall": 0.559228650137741,
            "f1-score": 0.5464333781965006,
            "support": 363.0
        },
        "17": {
            "precision": 0.4673704414587332,
            "recall": 0.8558875219683656,
            "f1-score": 0.6045934202358784,
            "support": 569.0
        },
        "18": {
            "precision": 0.8411405295315683,
            "recall": 0.7972972972972973,
            "f1-score": 0.8186323092170465,
            "support": 518.0
        },
        "19": {
            "precision": 0.8672768878718535,
            "recall": 0.8366445916114791,
            "f1-score": 0.851685393258427,
            "support": 453.0
        },
        "20": {
            "precision": 0.62778730703259,
            "recall": 0.9265822784810127,
            "f1-score": 0.7484662576687117,
            "support": 395.0
        },
        "21": {
            "precision": 0.8117469879518072,
            "recall": 0.875,
            "f1-score": 0.8421875,
            "support": 616.0
        },
        "22": {
            "precision": 0.8723051409618574,
            "recall": 0.9813432835820896,
            "f1-score": 0.9236172080772608,
            "support": 536.0
        },
        "23": {
            "precision": 0.8881491344873502,
            "recall": 0.9723032069970845,
            "f1-score": 0.9283228949199722,
            "support": 686.0
        },
        "24": {
            "precision": 0.85,
            "recall": 0.9725400457665904,
            "f1-score": 0.9071504802561366,
            "support": 437.0
        },
        "25": {
            "precision": 0.7808417997097242,
            "recall": 0.8226299694189603,
            "f1-score": 0.8011913626209978,
            "support": 654.0
        },
        "26": {
            "precision": 0.9432918395573997,
            "recall": 0.9841269841269841,
            "f1-score": 0.963276836158192,
            "support": 693.0
        },
        "27": {
            "precision": 0.7927927927927928,
            "recall": 0.7457627118644068,
            "f1-score": 0.7685589519650655,
            "support": 708.0
        },
        "28": {
            "precision": 0.6973478939157566,
            "recall": 0.9371069182389937,
            "f1-score": 0.7996422182468694,
            "support": 477.0
        },
        "29": {
            "precision": 0.8966165413533834,
            "recall": 0.8457446808510638,
            "f1-score": 0.8704379562043796,
            "support": 564.0
        },
        "30": {
            "precision": 0.6525679758308157,
            "recall": 0.7487001733102253,
            "f1-score": 0.6973365617433414,
            "support": 577.0
        },
        "31": {
            "precision": 0.8028455284552846,
            "recall": 0.8386411889596603,
            "f1-score": 0.8203530633437176,
            "support": 471.0
        },
        "32": {
            "precision": 0.927797833935018,
            "recall": 0.9390986601705238,
            "f1-score": 0.9334140435835351,
            "support": 821.0
        },
        "33": {
            "precision": 0.8978978978978979,
            "recall": 0.9101978691019786,
            "f1-score": 0.9040060468631897,
            "support": 657.0
        },
        "34": {
            "precision": 0.9728506787330317,
            "recall": 0.388086642599278,
            "f1-score": 0.5548387096774193,
            "support": 554.0
        },
        "35": {
            "precision": 0.6406593406593407,
            "recall": 0.9357945425361156,
            "f1-score": 0.7606001304631441,
            "support": 623.0
        },
        "36": {
            "precision": 0.8260869565217391,
            "recall": 0.8260869565217391,
            "f1-score": 0.8260869565217391,
            "support": 667.0
        },
        "37": {
            "precision": 0.688195991091314,
            "recall": 0.9701726844583988,
            "f1-score": 0.8052117263843648,
            "support": 637.0
        },
        "38": {
            "precision": 0.9166666666666666,
            "recall": 0.9828178694158075,
            "f1-score": 0.9485903814262023,
            "support": 582.0
        },
        "39": {
            "precision": 0.8765432098765432,
            "recall": 0.8833592534992224,
            "f1-score": 0.8799380325329202,
            "support": 643.0
        },
        "40": {
            "precision": 0.8586723768736617,
            "recall": 0.6207430340557275,
            "f1-score": 0.7205750224618149,
            "support": 646.0
        },
        "41": {
            "precision": 0.8213716108452951,
            "recall": 0.9644194756554307,
            "f1-score": 0.8871662360034454,
            "support": 534.0
        },
        "42": {
            "precision": 0.9186046511627907,
            "recall": 0.9011406844106464,
            "f1-score": 0.9097888675623801,
            "support": 526.0
        },
        "43": {
            "precision": 0.49326145552560646,
            "recall": 0.357421875,
            "f1-score": 0.4144960362400906,
            "support": 512.0
        },
        "44": {
            "precision": 0.7572815533980582,
            "recall": 0.18309859154929578,
            "f1-score": 0.2948960302457467,
            "support": 426.0
        },
        "45": {
            "precision": 0.989010989010989,
            "recall": 0.8548168249660787,
            "f1-score": 0.9170305676855895,
            "support": 737.0
        },
        "46": {
            "precision": 0.9705882352941176,
            "recall": 0.7795275590551181,
            "f1-score": 0.8646288209606987,
            "support": 635.0
        },
        "47": {
            "precision": 0.9656565656565657,
            "recall": 0.7198795180722891,
            "f1-score": 0.8248490077653149,
            "support": 664.0
        },
        "48": {
            "precision": 0.929553264604811,
            "recall": 0.8600953895071543,
            "f1-score": 0.893476465730801,
            "support": 629.0
        },
        "49": {
            "precision": 0.7978339350180506,
            "recall": 0.8752475247524752,
            "f1-score": 0.8347497639282342,
            "support": 505.0
        },
        "accuracy": 0.7968732997207008,
        "macro avg": {
            "precision": 0.80239196738468,
            "recall": 0.7831707504306296,
            "f1-score": 0.7716126408823076,
            "support": 27569.0
        },
        "weighted avg": {
            "precision": 0.8162261885988571,
            "recall": 0.7968732997207008,
            "f1-score": 0.787999418754245,
            "support": 27569.0
        }
    }
}