{
    "acc1": 0.7764338962422029,
    "acc5": [
        0.9463334854708657
    ],
    "mean_per_class_recall": 0.7725370234994972,
    "classification_report": {
        "0": {
            "precision": 0.8636363636363636,
            "recall": 0.8501945525291829,
            "f1-score": 0.8568627450980392,
            "support": 514.0
        },
        "1": {
            "precision": 0.8924050632911392,
            "recall": 0.8562753036437247,
            "f1-score": 0.8739669421487604,
            "support": 494.0
        },
        "2": {
            "precision": 0.8537549407114624,
            "recall": 0.8944099378881988,
            "f1-score": 0.8736097067745198,
            "support": 483.0
        },
        "3": {
            "precision": 0.42,
            "recall": 0.41935483870967744,
            "f1-score": 0.4196771714066103,
            "support": 651.0
        },
        "4": {
            "precision": 0.8836065573770492,
            "recall": 0.7973372781065089,
            "f1-score": 0.838258164852255,
            "support": 676.0
        },
        "5": {
            "precision": 0.1780821917808219,
            "recall": 0.03571428571428571,
            "f1-score": 0.059496567505720827,
            "support": 364.0
        },
        "6": {
            "precision": 0.9037940379403794,
            "recall": 0.9302649930264993,
            "f1-score": 0.9168384879725086,
            "support": 717.0
        },
        "7": {
            "precision": 0.5099750623441397,
            "recall": 0.9533799533799534,
            "f1-score": 0.6645004061738424,
            "support": 429.0
        },
        "8": {
            "precision": 0.7776280323450134,
            "recall": 0.9321486268174475,
            "f1-score": 0.8479059515062454,
            "support": 619.0
        },
        "9": {
            "precision": 0.8851851851851852,
            "recall": 0.9227799227799228,
            "f1-score": 0.9035916824196597,
            "support": 518.0
        },
        "10": {
            "precision": 0.8913043478260869,
            "recall": 0.7404063205417607,
            "f1-score": 0.8088779284833539,
            "support": 443.0
        },
        "11": {
            "precision": 0.8016877637130801,
            "recall": 0.40948275862068967,
            "f1-score": 0.5420827389443652,
            "support": 464.0
        },
        "12": {
            "precision": 0.8233995584988962,
            "recall": 0.979002624671916,
            "f1-score": 0.894484412470024,
            "support": 381.0
        },
        "13": {
            "precision": 0.9537712895377128,
            "recall": 0.8711111111111111,
            "f1-score": 0.9105691056910569,
            "support": 450.0
        },
        "14": {
            "precision": 0.8643617021276596,
            "recall": 0.9298998569384835,
            "f1-score": 0.895933838731909,
            "support": 699.0
        },
        "15": {
            "precision": 0.5950095969289827,
            "recall": 0.5730129390018485,
            "f1-score": 0.583804143126177,
            "support": 541.0
        },
        "16": {
            "precision": 0.8388349514563107,
            "recall": 0.8888888888888888,
            "f1-score": 0.8631368631368631,
            "support": 486.0
        },
        "17": {
            "precision": 0.8353174603174603,
            "recall": 0.8591836734693877,
            "f1-score": 0.8470824949698189,
            "support": 490.0
        },
        "18": {
            "precision": 0.8303886925795053,
            "recall": 0.6911764705882353,
            "f1-score": 0.7544141252006421,
            "support": 340.0
        },
        "19": {
            "precision": 0.7775768535262206,
            "recall": 0.9307359307359307,
            "f1-score": 0.8472906403940886,
            "support": 462.0
        },
        "20": {
            "precision": 0.9602977667493796,
            "recall": 0.88558352402746,
            "f1-score": 0.9214285714285714,
            "support": 437.0
        },
        "21": {
            "precision": 0.8220338983050848,
            "recall": 0.5038961038961038,
            "f1-score": 0.6247987117552335,
            "support": 385.0
        },
        "22": {
            "precision": 0.4543828264758497,
            "recall": 0.7537091988130564,
            "f1-score": 0.5669642857142857,
            "support": 337.0
        },
        "23": {
            "precision": 0.8411214953271028,
            "recall": 0.7964601769911505,
            "f1-score": 0.8181818181818182,
            "support": 339.0
        },
        "24": {
            "precision": 0.8088512241054614,
            "recall": 0.9439560439560439,
            "f1-score": 0.8711967545638946,
            "support": 910.0
        },
        "25": {
            "precision": 0.45322245322245325,
            "recall": 0.42248062015503873,
            "f1-score": 0.4373119358074223,
            "support": 516.0
        },
        "26": {
            "precision": 0.8864142538975501,
            "recall": 0.9212962962962963,
            "f1-score": 0.9035187287173666,
            "support": 432.0
        },
        "27": {
            "precision": 0.7727272727272727,
            "recall": 0.8075,
            "f1-score": 0.7897310513447433,
            "support": 400.0
        },
        "28": {
            "precision": 0.7372881355932204,
            "recall": 0.9560439560439561,
            "f1-score": 0.8325358851674641,
            "support": 364.0
        },
        "29": {
            "precision": 0.8769230769230769,
            "recall": 0.8814432989690721,
            "f1-score": 0.8791773778920309,
            "support": 388.0
        },
        "30": {
            "precision": 0.8356807511737089,
            "recall": 0.6391382405745063,
            "f1-score": 0.7243133265513734,
            "support": 557.0
        },
        "31": {
            "precision": 0.9155470249520153,
            "recall": 0.9120458891013384,
            "f1-score": 0.9137931034482759,
            "support": 523.0
        },
        "32": {
            "precision": 0.8180404354587869,
            "recall": 0.8067484662576687,
            "f1-score": 0.8123552123552124,
            "support": 652.0
        },
        "33": {
            "precision": 0.6694045174537988,
            "recall": 0.9261363636363636,
            "f1-score": 0.7771156138259833,
            "support": 352.0
        },
        "34": {
            "precision": 0.6392111368909513,
            "recall": 0.8412213740458016,
            "f1-score": 0.7264337508239948,
            "support": 655.0
        },
        "35": {
            "precision": 0.8794117647058823,
            "recall": 0.6242171189979123,
            "f1-score": 0.7301587301587301,
            "support": 479.0
        },
        "36": {
            "precision": 0.9057527539779682,
            "recall": 0.9002433090024331,
            "f1-score": 0.9029896278218426,
            "support": 822.0
        },
        "37": {
            "precision": 0.8328981723237598,
            "recall": 0.8644986449864499,
            "f1-score": 0.848404255319149,
            "support": 738.0
        },
        "38": {
            "precision": 0.9564541213063764,
            "recall": 0.8541666666666666,
            "f1-score": 0.9024211298606016,
            "support": 720.0
        },
        "39": {
            "precision": 0.6679841897233202,
            "recall": 0.7031900138696255,
            "f1-score": 0.6851351351351351,
            "support": 721.0
        },
        "40": {
            "precision": 0.8216432865731463,
            "recall": 0.7142857142857143,
            "f1-score": 0.7642124883504194,
            "support": 574.0
        },
        "41": {
            "precision": 0.9431438127090301,
            "recall": 0.7230769230769231,
            "f1-score": 0.818577648766328,
            "support": 780.0
        },
        "42": {
            "precision": 0.6573426573426573,
            "recall": 0.6337078651685393,
            "f1-score": 0.6453089244851259,
            "support": 445.0
        },
        "43": {
            "precision": 0.6183206106870229,
            "recall": 0.8653846153846154,
            "f1-score": 0.7212822796081924,
            "support": 468.0
        },
        "44": {
            "precision": 0.8649289099526066,
            "recall": 0.6552962298025135,
            "f1-score": 0.745658835546476,
            "support": 557.0
        },
        "45": {
            "precision": 0.47897196261682246,
            "recall": 0.775047258979206,
            "f1-score": 0.592057761732852,
            "support": 529.0
        },
        "46": {
            "precision": 0.0,
            "recall": 0.0,
            "f1-score": 0.0,
            "support": 588.0
        },
        "47": {
            "precision": 0.8840336134453781,
            "recall": 0.9443447037701975,
            "f1-score": 0.9131944444444444,
            "support": 557.0
        },
        "48": {
            "precision": 0.9141104294478528,
            "recall": 0.9717391304347827,
            "f1-score": 0.9420442571127503,
            "support": 460.0
        },
        "49": {
            "precision": 0.8148984198645598,
            "recall": 0.9352331606217616,
            "f1-score": 0.8709288299155609,
            "support": 386.0
        },
        "accuracy": 0.7761676555606268,
        "macro avg": {
            "precision": 0.7622152125011113,
            "recall": 0.7725370234994972,
            "f1-score": 0.7576722918568347,
            "support": 26292.0
        },
        "weighted avg": {
            "precision": 0.7687946377541366,
            "recall": 0.7761676555606268,
            "f1-score": 0.7640070926413312,
            "support": 26292.0
        }
    }
}