{
    "acc1": 0.5685379583143162,
    "acc5": [
        0.7716795983569147
    ],
    "mean_per_class_recall": 0.5484861872638631,
    "classification_report": {
        "0": {
            "precision": 0.9506726457399103,
            "recall": 0.8249027237354085,
            "f1-score": 0.8833333333333333,
            "support": 514.0
        },
        "1": {
            "precision": 0.0,
            "recall": 0.0,
            "f1-score": 0.0,
            "support": 494.0
        },
        "2": {
            "precision": 0.9818181818181818,
            "recall": 0.8944099378881988,
            "f1-score": 0.9360780065005417,
            "support": 483.0
        },
        "3": {
            "precision": 0.425531914893617,
            "recall": 0.030721966205837174,
            "f1-score": 0.05730659025787966,
            "support": 651.0
        },
        "4": {
            "precision": 0.6720321931589537,
            "recall": 0.4940828402366864,
            "f1-score": 0.5694799658994032,
            "support": 676.0
        },
        "5": {
            "precision": 0.18181818181818182,
            "recall": 0.005494505494505495,
            "f1-score": 0.010666666666666666,
            "support": 364.0
        },
        "6": {
            "precision": 0.27225755166931637,
            "recall": 0.9553695955369595,
            "f1-score": 0.42375502629137024,
            "support": 717.0
        },
        "7": {
            "precision": 0.0,
            "recall": 0.0,
            "f1-score": 0.0,
            "support": 429.0
        },
        "8": {
            "precision": 0.125,
            "recall": 0.0016155088852988692,
            "f1-score": 0.003189792663476874,
            "support": 619.0
        },
        "9": {
            "precision": 0.9430147058823529,
            "recall": 0.9903474903474904,
            "f1-score": 0.9661016949152542,
            "support": 518.0
        },
        "10": {
            "precision": 1.0,
            "recall": 0.3611738148984199,
            "f1-score": 0.5306799336650083,
            "support": 443.0
        },
        "11": {
            "precision": 0.0,
            "recall": 0.0,
            "f1-score": 0.0,
            "support": 464.0
        },
        "12": {
            "precision": 0.9767441860465116,
            "recall": 0.11023622047244094,
            "f1-score": 0.19811320754716982,
            "support": 381.0
        },
        "13": {
            "precision": 0.1,
            "recall": 0.0022222222222222222,
            "f1-score": 0.004347826086956522,
            "support": 450.0
        },
        "14": {
            "precision": 0.9559228650137741,
            "recall": 0.9928469241773963,
            "f1-score": 0.9740350877192983,
            "support": 699.0
        },
        "15": {
            "precision": 0.0,
            "recall": 0.0,
            "f1-score": 0.0,
            "support": 541.0
        },
        "16": {
            "precision": 0.8312387791741472,
            "recall": 0.9526748971193416,
            "f1-score": 0.887823585810163,
            "support": 486.0
        },
        "17": {
            "precision": 0.0,
            "recall": 0.0,
            "f1-score": 0.0,
            "support": 490.0
        },
        "18": {
            "precision": 0.0,
            "recall": 0.0,
            "f1-score": 0.0,
            "support": 340.0
        },
        "19": {
            "precision": 0.6612184249628529,
            "recall": 0.9632034632034632,
            "f1-score": 0.7841409691629956,
            "support": 462.0
        },
        "20": {
            "precision": 0.9545454545454546,
            "recall": 0.9130434782608695,
            "f1-score": 0.9333333333333333,
            "support": 437.0
        },
        "21": {
            "precision": 0.9886363636363636,
            "recall": 0.22597402597402597,
            "f1-score": 0.3678646934460888,
            "support": 385.0
        },
        "22": {
            "precision": 0.8354838709677419,
            "recall": 0.7685459940652819,
            "f1-score": 0.8006182380216383,
            "support": 337.0
        },
        "23": {
            "precision": 0.46543778801843316,
            "recall": 0.8938053097345132,
            "f1-score": 0.6121212121212121,
            "support": 339.0
        },
        "24": {
            "precision": 0.9330855018587361,
            "recall": 0.8274725274725274,
            "f1-score": 0.8771112405358182,
            "support": 910.0
        },
        "25": {
            "precision": 0.180341524364848,
            "recall": 0.8391472868217055,
            "f1-score": 0.29688035653068223,
            "support": 516.0
        },
        "26": {
            "precision": 0.9848484848484849,
            "recall": 0.9027777777777778,
            "f1-score": 0.9420289855072463,
            "support": 432.0
        },
        "27": {
            "precision": 0.7855227882037533,
            "recall": 0.7325,
            "f1-score": 0.7580853816300129,
            "support": 400.0
        },
        "28": {
            "precision": 0.27416666666666667,
            "recall": 0.9038461538461539,
            "f1-score": 0.42071611253196933,
            "support": 364.0
        },
        "29": {
            "precision": 0.8829516539440203,
            "recall": 0.8943298969072165,
            "f1-score": 0.8886043533930857,
            "support": 388.0
        },
        "30": {
            "precision": 1.0,
            "recall": 0.005385996409335727,
            "f1-score": 0.010714285714285714,
            "support": 557.0
        },
        "31": {
            "precision": 0.9510357815442562,
            "recall": 0.9655831739961759,
            "f1-score": 0.9582542694497154,
            "support": 523.0
        },
        "32": {
            "precision": 0.2114587259705993,
            "recall": 0.8604294478527608,
            "f1-score": 0.3394856278366112,
            "support": 652.0
        },
        "33": {
            "precision": 0.2894736842105263,
            "recall": 0.09375,
            "f1-score": 0.14163090128755365,
            "support": 352.0
        },
        "34": {
            "precision": 0.8105849582172702,
            "recall": 0.8885496183206106,
            "f1-score": 0.8477785870356883,
            "support": 655.0
        },
        "35": {
            "precision": 0.935,
            "recall": 0.7807933194154488,
            "f1-score": 0.850967007963595,
            "support": 479.0
        },
        "36": {
            "precision": 0.7673956262425448,
            "recall": 0.9391727493917275,
            "f1-score": 0.8446389496717724,
            "support": 822.0
        },
        "37": {
            "precision": 0.9776223776223776,
            "recall": 0.9471544715447154,
            "f1-score": 0.9621472814865795,
            "support": 738.0
        },
        "38": {
            "precision": 0.5,
            "recall": 0.009722222222222222,
            "f1-score": 0.01907356948228883,
            "support": 720.0
        },
        "39": {
            "precision": 0.5177304964539007,
            "recall": 0.10124826629680998,
            "f1-score": 0.16937354988399073,
            "support": 721.0
        },
        "40": {
            "precision": 0.32942555685814773,
            "recall": 0.9790940766550522,
            "f1-score": 0.49298245614035086,
            "support": 574.0
        },
        "41": {
            "precision": 0.9181141439205955,
            "recall": 0.9487179487179487,
            "f1-score": 0.9331651954602774,
            "support": 780.0
        },
        "42": {
            "precision": 0.4262295081967213,
            "recall": 0.058426966292134834,
            "f1-score": 0.10276679841897234,
            "support": 445.0
        },
        "43": {
            "precision": 0.0,
            "recall": 0.0,
            "f1-score": 0.0,
            "support": 468.0
        },
        "44": {
            "precision": 0.04081632653061224,
            "recall": 0.003590664272890485,
            "f1-score": 0.006600660066006601,
            "support": 557.0
        },
        "45": {
            "precision": 0.4411764705882353,
            "recall": 0.5671077504725898,
            "f1-score": 0.49627791563275436,
            "support": 529.0
        },
        "46": {
            "precision": 0.41589779985805536,
            "recall": 0.9965986394557823,
            "f1-score": 0.586880320480721,
            "support": 588.0
        },
        "47": {
            "precision": 0.9723756906077348,
            "recall": 0.947935368043088,
            "f1-score": 0.96,
            "support": 557.0
        },
        "48": {
            "precision": 0.8380952380952381,
            "recall": 0.9565217391304348,
            "f1-score": 0.8934010152284264,
            "support": 460.0
        },
        "49": {
            "precision": 0.8060747663551402,
            "recall": 0.8937823834196891,
            "f1-score": 0.8476658476658476,
            "support": 386.0
        },
        "accuracy": 0.5684999239312338,
        "macro avg": {
            "precision": 0.5702159375700852,
            "recall": 0.5484861872638631,
            "f1-score": 0.4918043966495208,
            "support": 26292.0
        },
        "weighted avg": {
            "precision": 0.5824165255073951,
            "recall": 0.5684999239312338,
            "f1-score": 0.5071573856770022,
            "support": 26292.0
        }
    }
}